Metadata-Version: 2.1
Name: qatamagochi
Version: 0.1.0
Summary: Testing a package can call another package inside
Home-page: https://github.com/danielmen-mx/qatamagochi
Author: Daniel Mendez
Author-email: pablomen1131@gmail.com
Classifier: Programming Language :: Python :: 3
Classifier: License :: OSI Approved :: MIT License
Classifier: Operating System :: OS Independent
Requires-Python: >=3.6
License-File: LICENSE
